[
{"route_index":0,"direction":193,"is_weekend":false},
{"route_index":0,"direction":193,"is_weekend":true},
{"route_index":0,"direction":194,"is_weekend":false},
{"route_index":0,"direction":194,"is_weekend":true},
{"route_index":1,"direction":161,"is_weekend":false},
{"route_index":1,"direction":161,"is_weekend":true},
{"route_index":1,"direction":160,"is_weekend":false},
{"route_index":1,"direction":160,"is_weekend":true},
{"route_index":2,"direction":21,"is_weekend":false},
{"route_index":2,"direction":21,"is_weekend":true},
{"route_index":2,"direction":22,"is_weekend":false},
{"route_index":2,"direction":22,"is_weekend":true},
{"route_index":3,"direction":496,"is_weekend":false},
{"route_index":3,"direction":496,"is_weekend":true},
{"route_index":3,"direction":497,"is_weekend":false},
{"route_index":3,"direction":497,"is_weekend":true},
{"route_index":4,"direction":301,"is_weekend":false},
{"route_index":4,"direction":301,"is_weekend":true},
{"route_index":4,"direction":302,"is_weekend":false},
{"route_index":4,"direction":302,"is_weekend":true},
{"route_index":5,"direction":249,"is_weekend":false},
{"route_index":5,"direction":249,"is_weekend":true},
{"route_index":5,"direction":250,"is_weekend":false},
{"route_index":5,"direction":250,"is_weekend":true},
{"route_index":6,"direction":293,"is_weekend":false},
{"route_index":6,"direction":293,"is_weekend":true},
{"route_index":6,"direction":294,"is_weekend":false},
{"route_index":6,"direction":294,"is_weekend":true},
{"route_index":7,"direction":178,"is_weekend":false},
{"route_index":7,"direction":178,"is_weekend":true},
{"route_index":7,"direction":179,"is_weekend":false},
{"route_index":7,"direction":179,"is_weekend":true},
{"route_index":8,"direction":475,"is_weekend":false},
{"route_index":8,"direction":475,"is_weekend":true},
{"route_index":8,"direction":476,"is_weekend":false},
{"route_index":8,"direction":476,"is_weekend":true},
{"route_index":9,"direction":439,"is_weekend":false},
{"route_index":9,"direction":439,"is_weekend":true},
{"route_index":9,"direction":440,"is_weekend":false},
{"route_index":9,"direction":440,"is_weekend":true},
{"route_index":10,"direction":187,"is_weekend":false},
{"route_index":10,"direction":187,"is_weekend":true},
{"route_index":10,"direction":188,"is_weekend":false},
{"route_index":10,"direction":188,"is_weekend":true},
{"route_index":11,"direction":100,"is_weekend":false},
{"route_index":11,"direction":100,"is_weekend":true},
{"route_index":11,"direction":101,"is_weekend":false},
{"route_index":11,"direction":101,"is_weekend":true},
{"route_index":12,"direction":123,"is_weekend":false},
{"route_index":12,"direction":123,"is_weekend":true},
{"route_index":12,"direction":124,"is_weekend":false},
{"route_index":12,"direction":124,"is_weekend":true},
{"route_index":13,"direction":345,"is_weekend":false},
{"route_index":13,"direction":345,"is_weekend":true},
{"route_index":13,"direction":346,"is_weekend":false},
{"route_index":13,"direction":346,"is_weekend":true},
{"route_index":14,"direction":23,"is_weekend":false},
{"route_index":14,"direction":23,"is_weekend":true},
{"route_index":14,"direction":24,"is_weekend":false},
{"route_index":14,"direction":24,"is_weekend":true},
{"route_index":15,"direction":88,"is_weekend":false},
{"route_index":15,"direction":88,"is_weekend":true},
{"route_index":15,"direction":89,"is_weekend":false},
{"route_index":15,"direction":89,"is_weekend":true},
{"route_index":16,"direction":291,"is_weekend":false},
{"route_index":16,"direction":291,"is_weekend":true},
{"route_index":16,"direction":292,"is_weekend":false},
{"route_index":16,"direction":292,"is_weekend":true},
{"route_index":17,"direction":353,"is_weekend":false},
{"route_index":17,"direction":354,"is_weekend":false},
{"route_index":17,"direction":355,"is_weekend":false},
{"route_index":17,"direction":356,"is_weekend":false},
{"route_index":18,"direction":385,"is_weekend":false},
{"route_index":18,"direction":385,"is_weekend":true},
{"route_index":18,"direction":386,"is_weekend":false},
{"route_index":18,"direction":386,"is_weekend":true},
{"route_index":18,"direction":388,"is_weekend":false},
{"route_index":18,"direction":388,"is_weekend":true},
{"route_index":18,"direction":390,"is_weekend":false},
{"route_index":18,"direction":390,"is_weekend":true},
{"route_index":18,"direction":391,"is_weekend":false},
{"route_index":18,"direction":391,"is_weekend":true},
{"route_index":18,"direction":392,"is_weekend":false},
{"route_index":18,"direction":392,"is_weekend":true},
{"route_index":19,"direction":306,"is_weekend":false},
{"route_index":19,"direction":306,"is_weekend":true},
{"route_index":19,"direction":307,"is_weekend":false},
{"route_index":19,"direction":307,"is_weekend":true},
{"route_index":20,"direction":469,"is_weekend":false},
{"route_index":20,"direction":469,"is_weekend":true},
{"route_index":20,"direction":470,"is_weekend":false},
{"route_index":20,"direction":470,"is_weekend":true},
{"route_index":21,"direction":154,"is_weekend":false},
{"route_index":21,"direction":154,"is_weekend":true},
{"route_index":21,"direction":155,"is_weekend":false},
{"route_index":21,"direction":155,"is_weekend":true},
{"route_index":22,"direction":94,"is_weekend":false},
{"route_index":22,"direction":94,"is_weekend":true},
{"route_index":22,"direction":95,"is_weekend":false},
{"route_index":22,"direction":95,"is_weekend":true},
{"route_index":23,"direction":110,"is_weekend":false},
{"route_index":23,"direction":110,"is_weekend":true},
{"route_index":23,"direction":114,"is_weekend":false},
{"route_index":23,"direction":114,"is_weekend":true},
{"route_index":23,"direction":111,"is_weekend":false},
{"route_index":23,"direction":111,"is_weekend":true},
{"route_index":24,"direction":285,"is_weekend":false},
{"route_index":24,"direction":285,"is_weekend":true},
{"route_index":24,"direction":289,"is_weekend":false},
{"route_index":24,"direction":289,"is_weekend":true},
{"route_index":24,"direction":286,"is_weekend":false},
{"route_index":24,"direction":286,"is_weekend":true},
{"route_index":25,"direction":498,"is_weekend":false},
{"route_index":25,"direction":498,"is_weekend":true},
{"route_index":25,"direction":502,"is_weekend":false},
{"route_index":25,"direction":499,"is_weekend":false},
{"route_index":25,"direction":499,"is_weekend":true},
{"route_index":26,"direction":166,"is_weekend":false},
{"route_index":26,"direction":166,"is_weekend":true},
{"route_index":26,"direction":167,"is_weekend":false},
{"route_index":26,"direction":167,"is_weekend":true},
{"route_index":27,"direction":460,"is_weekend":false},
{"route_index":27,"direction":460,"is_weekend":true},
{"route_index":27,"direction":461,"is_weekend":false},
{"route_index":27,"direction":461,"is_weekend":true},
{"route_index":28,"direction":29,"is_weekend":false},
{"route_index":28,"direction":29,"is_weekend":true},
{"route_index":28,"direction":30,"is_weekend":false},
{"route_index":28,"direction":30,"is_weekend":true},
{"route_index":29,"direction":5,"is_weekend":false},
{"route_index":29,"direction":5,"is_weekend":true},
{"route_index":29,"direction":6,"is_weekend":false},
{"route_index":29,"direction":6,"is_weekend":true},
{"route_index":30,"direction":435,"is_weekend":false},
{"route_index":30,"direction":435,"is_weekend":true},
{"route_index":30,"direction":436,"is_weekend":false},
{"route_index":30,"direction":436,"is_weekend":true},
{"route_index":31,"direction":60,"is_weekend":false},
{"route_index":31,"direction":60,"is_weekend":true},
{"route_index":31,"direction":65,"is_weekend":false},
{"route_index":31,"direction":61,"is_weekend":false},
{"route_index":31,"direction":61,"is_weekend":true},
{"route_index":31,"direction":63,"is_weekend":true},
{"route_index":31,"direction":64,"is_weekend":false},
{"route_index":32,"direction":381,"is_weekend":false},
{"route_index":33,"direction":398,"is_weekend":false},
{"route_index":34,"direction":246,"is_weekend":false},
{"route_index":34,"direction":246,"is_weekend":true},
{"route_index":34,"direction":247,"is_weekend":false},
{"route_index":34,"direction":247,"is_weekend":true},
{"route_index":35,"direction":336,"is_weekend":false},
{"route_index":35,"direction":336,"is_weekend":true},
{"route_index":35,"direction":337,"is_weekend":false},
{"route_index":35,"direction":337,"is_weekend":true},
{"route_index":36,"direction":427,"is_weekend":false},
{"route_index":36,"direction":427,"is_weekend":true},
{"route_index":36,"direction":429,"is_weekend":false},
{"route_index":36,"direction":428,"is_weekend":false},
{"route_index":36,"direction":428,"is_weekend":true},
{"route_index":36,"direction":430,"is_weekend":false},
{"route_index":37,"direction":458,"is_weekend":false},
{"route_index":37,"direction":458,"is_weekend":true},
{"route_index":37,"direction":459,"is_weekend":false},
{"route_index":37,"direction":459,"is_weekend":true},
{"route_index":38,"direction":505,"is_weekend":false},
{"route_index":38,"direction":506,"is_weekend":false},
{"route_index":39,"direction":360,"is_weekend":false},
{"route_index":39,"direction":362,"is_weekend":true},
{"route_index":39,"direction":364,"is_weekend":true},
{"route_index":39,"direction":361,"is_weekend":false},
{"route_index":39,"direction":361,"is_weekend":true},
{"route_index":39,"direction":368,"is_weekend":true},
{"route_index":39,"direction":363,"is_weekend":true},
{"route_index":40,"direction":315,"is_weekend":false},
{"route_index":40,"direction":315,"is_weekend":true},
{"route_index":40,"direction":316,"is_weekend":false},
{"route_index":40,"direction":316,"is_weekend":true},
{"route_index":41,"direction":456,"is_weekend":false},
{"route_index":41,"direction":457,"is_weekend":false},
{"route_index":42,"direction":415,"is_weekend":false},
{"route_index":42,"direction":415,"is_weekend":true},
{"route_index":42,"direction":416,"is_weekend":false},
{"route_index":42,"direction":416,"is_weekend":true},
{"route_index":43,"direction":325,"is_weekend":false},
{"route_index":43,"direction":326,"is_weekend":false},
{"route_index":43,"direction":327,"is_weekend":false},
{"route_index":44,"direction":516,"is_weekend":false},
{"route_index":44,"direction":516,"is_weekend":true},
{"route_index":44,"direction":517,"is_weekend":false},
{"route_index":44,"direction":517,"is_weekend":true},
{"route_index":45,"direction":320,"is_weekend":false},
{"route_index":45,"direction":320,"is_weekend":true},
{"route_index":45,"direction":321,"is_weekend":false},
{"route_index":45,"direction":321,"is_weekend":true},
{"route_index":46,"direction":116,"is_weekend":false},
{"route_index":46,"direction":116,"is_weekend":true},
{"route_index":46,"direction":117,"is_weekend":false},
{"route_index":46,"direction":117,"is_weekend":true},
{"route_index":47,"direction":413,"is_weekend":false},
{"route_index":47,"direction":413,"is_weekend":true},
{"route_index":47,"direction":414,"is_weekend":false},
{"route_index":47,"direction":414,"is_weekend":true},
{"route_index":48,"direction":44,"is_weekend":false},
{"route_index":48,"direction":44,"is_weekend":true},
{"route_index":48,"direction":46,"is_weekend":false},
{"route_index":48,"direction":46,"is_weekend":true},
{"route_index":48,"direction":45,"is_weekend":false},
{"route_index":48,"direction":45,"is_weekend":true},
{"route_index":48,"direction":47,"is_weekend":false},
{"route_index":48,"direction":47,"is_weekend":true},
{"route_index":49,"direction":10,"is_weekend":false},
{"route_index":49,"direction":10,"is_weekend":true},
{"route_index":49,"direction":11,"is_weekend":false},
{"route_index":49,"direction":11,"is_weekend":true},
{"route_index":50,"direction":431,"is_weekend":false},
{"route_index":50,"direction":431,"is_weekend":true},
{"route_index":50,"direction":432,"is_weekend":false},
{"route_index":50,"direction":432,"is_weekend":true},
{"route_index":51,"direction":445,"is_weekend":false},
{"route_index":51,"direction":445,"is_weekend":true},
{"route_index":51,"direction":446,"is_weekend":false},
{"route_index":51,"direction":446,"is_weekend":true},
{"route_index":52,"direction":407,"is_weekend":false},
{"route_index":52,"direction":407,"is_weekend":true},
{"route_index":52,"direction":405,"is_weekend":false},
{"route_index":52,"direction":406,"is_weekend":false},
{"route_index":52,"direction":406,"is_weekend":true},
{"route_index":52,"direction":408,"is_weekend":false},
{"route_index":52,"direction":409,"is_weekend":false},
{"route_index":53,"direction":340,"is_weekend":false},
{"route_index":53,"direction":340,"is_weekend":true},
{"route_index":53,"direction":341,"is_weekend":false},
{"route_index":53,"direction":341,"is_weekend":true},
{"route_index":54,"direction":75,"is_weekend":false},
{"route_index":54,"direction":75,"is_weekend":true},
{"route_index":54,"direction":76,"is_weekend":false},
{"route_index":54,"direction":76,"is_weekend":true},
{"route_index":55,"direction":182,"is_weekend":false},
{"route_index":55,"direction":182,"is_weekend":true},
{"route_index":55,"direction":185,"is_weekend":false},
{"route_index":55,"direction":185,"is_weekend":true},
{"route_index":55,"direction":186,"is_weekend":false},
{"route_index":55,"direction":186,"is_weekend":true},
{"route_index":55,"direction":183,"is_weekend":false},
{"route_index":55,"direction":183,"is_weekend":true},
{"route_index":56,"direction":481,"is_weekend":false},
{"route_index":56,"direction":481,"is_weekend":true},
{"route_index":56,"direction":482,"is_weekend":false},
{"route_index":56,"direction":482,"is_weekend":true},
{"route_index":57,"direction":141,"is_weekend":false},
{"route_index":57,"direction":141,"is_weekend":true},
{"route_index":57,"direction":142,"is_weekend":false},
{"route_index":57,"direction":142,"is_weekend":true},
{"route_index":58,"direction":263,"is_weekend":false},
{"route_index":58,"direction":263,"is_weekend":true},
{"route_index":58,"direction":264,"is_weekend":false},
{"route_index":58,"direction":264,"is_weekend":true},
{"route_index":59,"direction":322,"is_weekend":false},
{"route_index":59,"direction":322,"is_weekend":true},
{"route_index":59,"direction":324,"is_weekend":false},
{"route_index":59,"direction":323,"is_weekend":false},
{"route_index":59,"direction":323,"is_weekend":true},
{"route_index":60,"direction":38,"is_weekend":true},
{"route_index":60,"direction":39,"is_weekend":true},
{"route_index":61,"direction":35,"is_weekend":false},
{"route_index":61,"direction":35,"is_weekend":true},
{"route_index":61,"direction":36,"is_weekend":false},
{"route_index":61,"direction":36,"is_weekend":true},
{"route_index":61,"direction":37,"is_weekend":false},
{"route_index":62,"direction":56,"is_weekend":false},
{"route_index":62,"direction":56,"is_weekend":true},
{"route_index":62,"direction":58,"is_weekend":false},
{"route_index":62,"direction":57,"is_weekend":false},
{"route_index":62,"direction":57,"is_weekend":true},
{"route_index":62,"direction":59,"is_weekend":false},
{"route_index":63,"direction":118,"is_weekend":false},
{"route_index":63,"direction":118,"is_weekend":true},
{"route_index":63,"direction":120,"is_weekend":false},
{"route_index":63,"direction":119,"is_weekend":false},
{"route_index":63,"direction":119,"is_weekend":true},
{"route_index":64,"direction":328,"is_weekend":true},
{"route_index":64,"direction":329,"is_weekend":true},
{"route_index":65,"direction":281,"is_weekend":false},
{"route_index":65,"direction":281,"is_weekend":true},
{"route_index":65,"direction":282,"is_weekend":false},
{"route_index":65,"direction":282,"is_weekend":true},
{"route_index":66,"direction":139,"is_weekend":false},
{"route_index":66,"direction":139,"is_weekend":true},
{"route_index":66,"direction":140,"is_weekend":false},
{"route_index":66,"direction":140,"is_weekend":true},
{"route_index":67,"direction":195,"is_weekend":false},
{"route_index":67,"direction":196,"is_weekend":false},
{"route_index":68,"direction":275,"is_weekend":false},
{"route_index":68,"direction":275,"is_weekend":true},
{"route_index":68,"direction":276,"is_weekend":false},
{"route_index":68,"direction":276,"is_weekend":true},
{"route_index":69,"direction":338,"is_weekend":false},
{"route_index":69,"direction":338,"is_weekend":true},
{"route_index":69,"direction":339,"is_weekend":false},
{"route_index":69,"direction":339,"is_weekend":true},
{"route_index":70,"direction":201,"is_weekend":false},
{"route_index":70,"direction":201,"is_weekend":true},
{"route_index":70,"direction":204,"is_weekend":true},
{"route_index":70,"direction":202,"is_weekend":false},
{"route_index":70,"direction":202,"is_weekend":true},
{"route_index":71,"direction":70,"is_weekend":false},
{"route_index":71,"direction":70,"is_weekend":true},
{"route_index":71,"direction":73,"is_weekend":true},
{"route_index":71,"direction":71,"is_weekend":false},
{"route_index":71,"direction":71,"is_weekend":true},
{"route_index":71,"direction":74,"is_weekend":true},
{"route_index":71,"direction":72,"is_weekend":false},
{"route_index":71,"direction":72,"is_weekend":true},
{"route_index":72,"direction":357,"is_weekend":false},
{"route_index":72,"direction":357,"is_weekend":true},
{"route_index":72,"direction":358,"is_weekend":false},
{"route_index":72,"direction":358,"is_weekend":true},
{"route_index":73,"direction":279,"is_weekend":false},
{"route_index":73,"direction":279,"is_weekend":true},
{"route_index":73,"direction":280,"is_weekend":false},
{"route_index":73,"direction":280,"is_weekend":true},
{"route_index":74,"direction":145,"is_weekend":false},
{"route_index":74,"direction":145,"is_weekend":true},
{"route_index":74,"direction":146,"is_weekend":false},
{"route_index":74,"direction":146,"is_weekend":true},
{"route_index":75,"direction":269,"is_weekend":false},
{"route_index":75,"direction":270,"is_weekend":false},
{"route_index":76,"direction":12,"is_weekend":false},
{"route_index":76,"direction":12,"is_weekend":true},
{"route_index":76,"direction":18,"is_weekend":false},
{"route_index":76,"direction":18,"is_weekend":true},
{"route_index":76,"direction":15,"is_weekend":false},
{"route_index":76,"direction":16,"is_weekend":false},
{"route_index":76,"direction":16,"is_weekend":true},
{"route_index":76,"direction":13,"is_weekend":false},
{"route_index":76,"direction":13,"is_weekend":true},
{"route_index":76,"direction":14,"is_weekend":false},
{"route_index":76,"direction":20,"is_weekend":false},
{"route_index":76,"direction":20,"is_weekend":true},
{"route_index":77,"direction":489,"is_weekend":false},
{"route_index":77,"direction":489,"is_weekend":true},
{"route_index":77,"direction":490,"is_weekend":false},
{"route_index":77,"direction":490,"is_weekend":true},
{"route_index":77,"direction":491,"is_weekend":false},
{"route_index":77,"direction":491,"is_weekend":true},
{"route_index":78,"direction":521,"is_weekend":false},
{"route_index":78,"direction":521,"is_weekend":true},
{"route_index":78,"direction":522,"is_weekend":false},
{"route_index":78,"direction":522,"is_weekend":true},
{"route_index":79,"direction":234,"is_weekend":false},
{"route_index":79,"direction":234,"is_weekend":true},
{"route_index":79,"direction":239,"is_weekend":false},
{"route_index":79,"direction":239,"is_weekend":true},
{"route_index":79,"direction":235,"is_weekend":false},
{"route_index":79,"direction":235,"is_weekend":true},
{"route_index":79,"direction":245,"is_weekend":false},
{"route_index":80,"direction":86,"is_weekend":false},
{"route_index":80,"direction":86,"is_weekend":true},
{"route_index":80,"direction":87,"is_weekend":false},
{"route_index":80,"direction":87,"is_weekend":true},
{"route_index":81,"direction":129,"is_weekend":false},
{"route_index":81,"direction":130,"is_weekend":false},
{"route_index":82,"direction":226,"is_weekend":false},
{"route_index":82,"direction":226,"is_weekend":true},
{"route_index":82,"direction":227,"is_weekend":false},
{"route_index":82,"direction":227,"is_weekend":true},
{"route_index":83,"direction":299,"is_weekend":false},
{"route_index":83,"direction":299,"is_weekend":true},
{"route_index":83,"direction":300,"is_weekend":false},
{"route_index":83,"direction":300,"is_weekend":true},
{"route_index":84,"direction":197,"is_weekend":false},
{"route_index":84,"direction":197,"is_weekend":true},
{"route_index":84,"direction":198,"is_weekend":false},
{"route_index":84,"direction":198,"is_weekend":true},
{"route_index":85,"direction":205,"is_weekend":false},
{"route_index":85,"direction":205,"is_weekend":true},
{"route_index":85,"direction":206,"is_weekend":false},
{"route_index":85,"direction":206,"is_weekend":true},
{"route_index":86,"direction":310,"is_weekend":false},
{"route_index":86,"direction":310,"is_weekend":true},
{"route_index":86,"direction":313,"is_weekend":false},
{"route_index":86,"direction":313,"is_weekend":true},
{"route_index":86,"direction":311,"is_weekend":false},
{"route_index":86,"direction":311,"is_weekend":true},
{"route_index":86,"direction":314,"is_weekend":false},
{"route_index":86,"direction":314,"is_weekend":true},
{"route_index":87,"direction":52,"is_weekend":false},
{"route_index":87,"direction":52,"is_weekend":true},
{"route_index":87,"direction":53,"is_weekend":false},
{"route_index":87,"direction":53,"is_weekend":true},
{"route_index":88,"direction":419,"is_weekend":false},
{"route_index":88,"direction":419,"is_weekend":true},
{"route_index":88,"direction":420,"is_weekend":false},
{"route_index":88,"direction":420,"is_weekend":true},
{"route_index":89,"direction":375,"is_weekend":false},
{"route_index":89,"direction":375,"is_weekend":true},
{"route_index":89,"direction":377,"is_weekend":false},
{"route_index":89,"direction":377,"is_weekend":true},
{"route_index":89,"direction":376,"is_weekend":false},
{"route_index":89,"direction":376,"is_weekend":true},
{"route_index":90,"direction":209,"is_weekend":false},
{"route_index":90,"direction":209,"is_weekend":true},
{"route_index":90,"direction":210,"is_weekend":false},
{"route_index":90,"direction":210,"is_weekend":true},
{"route_index":91,"direction":214,"is_weekend":false},
{"route_index":91,"direction":214,"is_weekend":true},
{"route_index":91,"direction":215,"is_weekend":false},
{"route_index":91,"direction":215,"is_weekend":true},
{"route_index":92,"direction":492,"is_weekend":false},
{"route_index":92,"direction":492,"is_weekend":true},
{"route_index":92,"direction":493,"is_weekend":false},
{"route_index":92,"direction":493,"is_weekend":true},
{"route_index":93,"direction":8,"is_weekend":false},
{"route_index":93,"direction":8,"is_weekend":true},
{"route_index":93,"direction":9,"is_weekend":false},
{"route_index":93,"direction":9,"is_weekend":true},
{"route_index":94,"direction":382,"is_weekend":false},
{"route_index":94,"direction":382,"is_weekend":true},
{"route_index":94,"direction":383,"is_weekend":false},
{"route_index":94,"direction":383,"is_weekend":true},
{"route_index":94,"direction":384,"is_weekend":false},
{"route_index":94,"direction":384,"is_weekend":true},
{"route_index":95,"direction":265,"is_weekend":false},
{"route_index":95,"direction":265,"is_weekend":true},
{"route_index":95,"direction":266,"is_weekend":false},
{"route_index":95,"direction":266,"is_weekend":true},
{"route_index":96,"direction":330,"is_weekend":false},
{"route_index":96,"direction":330,"is_weekend":true},
{"route_index":96,"direction":331,"is_weekend":false},
{"route_index":96,"direction":331,"is_weekend":true},
{"route_index":97,"direction":437,"is_weekend":false},
{"route_index":97,"direction":437,"is_weekend":true},
{"route_index":97,"direction":438,"is_weekend":false},
{"route_index":97,"direction":438,"is_weekend":true},
{"route_index":98,"direction":133,"is_weekend":false},
{"route_index":98,"direction":133,"is_weekend":true},
{"route_index":98,"direction":134,"is_weekend":false},
{"route_index":98,"direction":134,"is_weekend":true},
{"route_index":99,"direction":143,"is_weekend":true},
{"route_index":99,"direction":144,"is_weekend":true},
{"route_index":100,"direction":229,"is_weekend":false},
{"route_index":100,"direction":229,"is_weekend":true},
{"route_index":100,"direction":231,"is_weekend":false},
{"route_index":100,"direction":231,"is_weekend":true},
{"route_index":100,"direction":230,"is_weekend":false},
{"route_index":100,"direction":230,"is_weekend":true},
{"route_index":101,"direction":261,"is_weekend":false},
{"route_index":101,"direction":261,"is_weekend":true},
{"route_index":101,"direction":262,"is_weekend":false},
{"route_index":101,"direction":262,"is_weekend":true},
{"route_index":102,"direction":369,"is_weekend":false},
{"route_index":102,"direction":369,"is_weekend":true},
{"route_index":102,"direction":374,"is_weekend":false},
{"route_index":102,"direction":374,"is_weekend":true},
{"route_index":102,"direction":370,"is_weekend":false},
{"route_index":102,"direction":370,"is_weekend":true},
{"route_index":102,"direction":372,"is_weekend":false},
{"route_index":102,"direction":372,"is_weekend":true},
{"route_index":103,"direction":410,"is_weekend":false},
{"route_index":103,"direction":410,"is_weekend":true},
{"route_index":103,"direction":411,"is_weekend":false},
{"route_index":103,"direction":411,"is_weekend":true},
{"route_index":104,"direction":176,"is_weekend":false},
{"route_index":104,"direction":176,"is_weekend":true},
{"route_index":104,"direction":177,"is_weekend":false},
{"route_index":104,"direction":177,"is_weekend":true},
{"route_index":105,"direction":69,"is_weekend":false},
{"route_index":105,"direction":69,"is_weekend":true},
{"route_index":105,"direction":67,"is_weekend":false},
{"route_index":105,"direction":67,"is_weekend":true},
{"route_index":105,"direction":68,"is_weekend":false},
{"route_index":105,"direction":68,"is_weekend":true},
{"route_index":106,"direction":317,"is_weekend":false},
{"route_index":106,"direction":317,"is_weekend":true},
{"route_index":106,"direction":318,"is_weekend":false},
{"route_index":106,"direction":318,"is_weekend":true},
{"route_index":107,"direction":396,"is_weekend":false},
{"route_index":107,"direction":396,"is_weekend":true},
{"route_index":107,"direction":397,"is_weekend":false},
{"route_index":107,"direction":397,"is_weekend":true},
{"route_index":108,"direction":77,"is_weekend":false},
{"route_index":108,"direction":77,"is_weekend":true},
{"route_index":108,"direction":80,"is_weekend":false},
{"route_index":108,"direction":80,"is_weekend":true},
{"route_index":108,"direction":78,"is_weekend":false},
{"route_index":108,"direction":78,"is_weekend":true},
{"route_index":109,"direction":512,"is_weekend":false},
{"route_index":109,"direction":512,"is_weekend":true},
{"route_index":109,"direction":513,"is_weekend":false},
{"route_index":109,"direction":513,"is_weekend":true},
{"route_index":110,"direction":504,"is_weekend":true},
{"route_index":111,"direction":81,"is_weekend":false},
{"route_index":111,"direction":81,"is_weekend":true},
{"route_index":111,"direction":82,"is_weekend":false},
{"route_index":111,"direction":85,"is_weekend":true},
{"route_index":111,"direction":83,"is_weekend":true},
{"route_index":112,"direction":379,"is_weekend":false},
{"route_index":112,"direction":379,"is_weekend":true},
{"route_index":112,"direction":380,"is_weekend":false},
{"route_index":112,"direction":380,"is_weekend":true},
{"route_index":113,"direction":507,"is_weekend":false},
{"route_index":113,"direction":507,"is_weekend":true},
{"route_index":113,"direction":508,"is_weekend":false},
{"route_index":113,"direction":508,"is_weekend":true},
{"route_index":113,"direction":510,"is_weekend":false},
{"route_index":113,"direction":510,"is_weekend":true},
{"route_index":114,"direction":401,"is_weekend":false},
{"route_index":114,"direction":401,"is_weekend":true},
{"route_index":114,"direction":402,"is_weekend":false},
{"route_index":114,"direction":402,"is_weekend":true},
{"route_index":114,"direction":403,"is_weekend":false},
{"route_index":114,"direction":403,"is_weekend":true},
{"route_index":115,"direction":216,"is_weekend":false},
{"route_index":115,"direction":216,"is_weekend":true},
{"route_index":115,"direction":217,"is_weekend":false},
{"route_index":115,"direction":217,"is_weekend":true},
{"route_index":116,"direction":3,"is_weekend":false},
{"route_index":116,"direction":3,"is_weekend":true},
{"route_index":116,"direction":4,"is_weekend":false},
{"route_index":116,"direction":4,"is_weekend":true},
{"route_index":117,"direction":466,"is_weekend":false},
{"route_index":117,"direction":467,"is_weekend":false},
{"route_index":118,"direction":1,"is_weekend":false},
{"route_index":118,"direction":1,"is_weekend":true},
{"route_index":118,"direction":2,"is_weekend":false},
{"route_index":118,"direction":2,"is_weekend":true},
{"route_index":119,"direction":106,"is_weekend":false},
{"route_index":119,"direction":106,"is_weekend":true},
{"route_index":119,"direction":107,"is_weekend":false},
{"route_index":119,"direction":107,"is_weekend":true},
{"route_index":120,"direction":447,"is_weekend":false},
{"route_index":120,"direction":447,"is_weekend":true},
{"route_index":120,"direction":448,"is_weekend":false},
{"route_index":120,"direction":448,"is_weekend":true},
{"route_index":121,"direction":151,"is_weekend":false},
{"route_index":121,"direction":151,"is_weekend":true},
{"route_index":121,"direction":152,"is_weekend":false},
{"route_index":121,"direction":152,"is_weekend":true},
{"route_index":122,"direction":494,"is_weekend":false},
{"route_index":122,"direction":494,"is_weekend":true},
{"route_index":122,"direction":495,"is_weekend":false},
{"route_index":122,"direction":495,"is_weekend":true},
{"route_index":123,"direction":425,"is_weekend":false},
{"route_index":123,"direction":425,"is_weekend":true},
{"route_index":123,"direction":426,"is_weekend":false},
{"route_index":123,"direction":426,"is_weekend":true},
{"route_index":124,"direction":452,"is_weekend":false},
{"route_index":124,"direction":452,"is_weekend":true},
{"route_index":124,"direction":453,"is_weekend":false},
{"route_index":124,"direction":453,"is_weekend":true},
{"route_index":125,"direction":222,"is_weekend":false},
{"route_index":125,"direction":222,"is_weekend":true},
{"route_index":125,"direction":223,"is_weekend":false},
{"route_index":125,"direction":223,"is_weekend":true},
{"route_index":126,"direction":218,"is_weekend":false},
{"route_index":126,"direction":220,"is_weekend":true},
{"route_index":126,"direction":219,"is_weekend":false},
{"route_index":126,"direction":221,"is_weekend":true},
{"route_index":127,"direction":395,"is_weekend":false},
{"route_index":128,"direction":40,"is_weekend":false},
{"route_index":128,"direction":41,"is_weekend":false},
{"route_index":128,"direction":42,"is_weekend":false},
{"route_index":129,"direction":283,"is_weekend":false},
{"route_index":129,"direction":284,"is_weekend":false},
{"route_index":130,"direction":121,"is_weekend":false},
{"route_index":130,"direction":122,"is_weekend":false},
{"route_index":131,"direction":164,"is_weekend":false},
{"route_index":131,"direction":164,"is_weekend":true},
{"route_index":131,"direction":165,"is_weekend":false},
{"route_index":131,"direction":165,"is_weekend":true},
{"route_index":132,"direction":351,"is_weekend":false},
{"route_index":132,"direction":351,"is_weekend":true},
{"route_index":132,"direction":352,"is_weekend":false},
{"route_index":132,"direction":352,"is_weekend":true},
{"route_index":133,"direction":108,"is_weekend":false},
{"route_index":133,"direction":108,"is_weekend":true},
{"route_index":133,"direction":109,"is_weekend":false},
{"route_index":133,"direction":109,"is_weekend":true},
{"route_index":134,"direction":48,"is_weekend":false},
{"route_index":134,"direction":48,"is_weekend":true},
{"route_index":134,"direction":49,"is_weekend":false},
{"route_index":134,"direction":49,"is_weekend":true},
{"route_index":135,"direction":273,"is_weekend":false},
{"route_index":135,"direction":273,"is_weekend":true},
{"route_index":135,"direction":274,"is_weekend":false},
{"route_index":135,"direction":274,"is_weekend":true}
]